orjsonic/__init__.py
orjsonic/orjsonic.py
orjsonic-0.1.7.dist-info/licenses/LICENSE
orjsonic-0.1.7.dist-info/METADATA
orjsonic-0.1.7.dist-info/WHEEL
orjsonic-0.1.7.dist-info/top_level.txt
orjsonic-0.1.7.dist-info/RECORD
