Metadata-Version: 2.4
Name: orjsonic
Version: 0.1.7
Summary: A fleixible and fast wrapper around orjson for custom JSON encoding/decoding
Author-email: randomseed42 <randomseed42@protonmail.com>
Project-URL: Homepage, https://github.com/randomseed42/orjsonic
Keywords: json,orjson,custom,encoding,decoding
Classifier: Development Status :: 4 - Beta
Classifier: Intended Audience :: Developers
Classifier: Programming Language :: Python :: 3
Classifier: Topic :: Software Development :: Libraries
Requires-Python: >=3.10
License-File: LICENSE
Requires-Dist: chardet
Requires-Dist: numpy
Requires-Dist: orjson
Requires-Dist: pandas
Dynamic: license-file
